.gitignore
LICENSE.txt
MANIFEST.in
README.md
howto-publish.txt
setup.cfg
setup.py
rlxutils/__init__.py
rlxutils/optimization.py
rlxutils/rlxutils.py
rlxutils.egg-info/PKG-INFO
rlxutils.egg-info/SOURCES.txt
rlxutils.egg-info/dependency_links.txt
rlxutils.egg-info/not-zip-safe
rlxutils.egg-info/requires.txt
rlxutils.egg-info/top_level.txt
rlxutils/__pycache__/__init__.cpython-38.pyc
rlxutils/__pycache__/optimization.cpython-38.pyc
rlxutils/__pycache__/rlxutils.cpython-38.pyc
rlxutils/__pycache__/utils.cpython-38.pyc
rlxutils/__pycache__/version.cpython-38.pyc