Metadata-Version: 2.1
Name: rlxutils
Version: 0.1.8
Summary: rlx general purpose utils
Home-page: https://github.com/rramosp/rlxutils/
Author: raul ramos
Author-email: rramosp@unal.edu.co
License: UNKNOWN
Platform: UNKNOWN
License-File: LICENSE.txt
